ghost2md/__init__.py
ghost2md/ghost2md.py
ghost2md/test.json
ghost2md-0.1.0.dist-info/entry_points.txt
ghost2md-0.1.0.dist-info/WHEEL
ghost2md-0.1.0.dist-info/METADATA
ghost2md-0.1.0.dist-info/RECORD
