Metadata-Version: 2.1
Name: ghost2md
Version: 0.1.0
Summary: Convert Ghost articles to markdown files
Home-page: https://github.com/mjdubell/ghost2md
Author: Michael Dubell
Author-email: michael@dubell.io
Requires-Python: >=3.4
Classifier: Programming Language :: Python :: 3
Classifier: Programming Language :: Python :: 3.4
Classifier: Programming Language :: Python :: 3.5
Classifier: Programming Language :: Python :: 3.6
Classifier: Programming Language :: Python :: 3.7
Project-URL: Repository, https://github.com/mjdubell/ghost2md
